setup.py
capless/__init__.py
capless/test_urls.py
capless/test_views.py
capless.egg-info/PKG-INFO
capless.egg-info/SOURCES.txt
capless.egg-info/dependency_links.txt
capless.egg-info/requires.txt
capless.egg-info/top_level.txt
capless/cli/__init__.py
capless/cli/cli.py
capless/core/__init__.py
capless/core/conf.py
capless/core/exceptions.py
capless/core/loading/__init__.py
capless/core/loading/templates.py
capless/core/urls/__init__.py
capless/core/urls/utils.py
capless/core/views/__init__.py
capless/core/views/apigw.py
capless/core/views/dbms.py
capless/core/views/s3.py
capless/core/views/events/__init__.py
capless/utils/__init__.py
example/__init__.py
example/blog/__init__.py
example/blog/models.py
example/blog/views.py
example/blog/commands/__init__.py
example/example/__init__.py
example/example/settings.py