Metadata-Version: 1.0
Name: capless
Version: 0.1.0
Summary: Python Serverless Framework
Home-page: https://github.com/capless/capless
Author: Brian Jinwright
Author-email: UNKNOWN
License: GNU GPL v3
Keywords: serverless,framework,
Platform: UNKNOWN
